MANIFEST.in
README.md
requirements.txt
setup.cfg
setup.py
pykronos/__init__.py
pykronos/client.py
pykronos/errors.py
pykronos/version.py
pykronos.egg-info/PKG-INFO
pykronos.egg-info/SOURCES.txt
pykronos.egg-info/dependency_links.txt
pykronos.egg-info/requires.txt
pykronos.egg-info/top_level.txt
pykronos/common/__init__.py
pykronos/common/cache.py
pykronos/common/cloudpickle.py
pykronos/common/concurrent.py
pykronos/common/decorators.py
pykronos/common/event_tools.py
pykronos/common/json_schema.py
pykronos/common/lazy.py
pykronos/common/readmeify.py
pykronos/common/runner.py
pykronos/common/settings.py
pykronos/common/time.py
pykronos/utils/__init__.py
pykronos/utils/cache.py
pykronos/utils/django.py