Metadata-Version: 1.1
Name: pykronos
Version: 0.6.2
Summary: A Python client for the Kronos time series storage engine
Home-page: https://github.com/Locu/chronology/pykronos
Author: GoDaddy
Author-email: devs@locu.com
License: MIT License
Keywords: kronos,analytics,metrics,client,logging
Platform: UNKNOWN
Classifier: Intended Audience :: Developers
Classifier: License :: OSI Approved :: MIT License
Classifier: Operating System :: OS Independent
Classifier: Programming Language :: Python
Classifier: Programming Language :: Python :: 2
Classifier: Programming Language :: Python :: 2.7
